django_jsonattrs-0.1.26.dist-info/METADATA
django_jsonattrs-0.1.26.dist-info/RECORD
django_jsonattrs-0.1.26.dist-info/WHEEL
django_jsonattrs-0.1.26.dist-info/top_level.txt
jsonattrs/__init__.py
jsonattrs/decorators.py
jsonattrs/exceptions.py
jsonattrs/fields.py
jsonattrs/forms.py
jsonattrs/mixins.py
jsonattrs/models.py
jsonattrs/signals.py
jsonattrs/__pycache__/__init__.cpython-35.pyc
jsonattrs/__pycache__/decorators.cpython-35.pyc
jsonattrs/__pycache__/exceptions.cpython-35.pyc
jsonattrs/__pycache__/fields.cpython-35.pyc
jsonattrs/__pycache__/forms.cpython-35.pyc
jsonattrs/__pycache__/mixins.cpython-35.pyc
jsonattrs/__pycache__/models.cpython-35.pyc
jsonattrs/__pycache__/signals.cpython-35.pyc
jsonattrs/management/__init__.py
jsonattrs/management/__pycache__/__init__.cpython-35.pyc
jsonattrs/management/commands/__init__.py
jsonattrs/management/commands/loadattrtypes.py
jsonattrs/management/commands/__pycache__/__init__.cpython-35.pyc
jsonattrs/management/commands/__pycache__/loadattrtypes.cpython-35.pyc
jsonattrs/migrations/0001_initial.py
jsonattrs/migrations/0002_attribute_choice_labels.py
jsonattrs/migrations/0003_prepare_multilingual_setup.py
jsonattrs/migrations/0004_convert_multilingual_fields.py
jsonattrs/migrations/0005_remove_monolingual_fields.py
jsonattrs/migrations/__init__.py
jsonattrs/migrations/__pycache__/0001_initial.cpython-35.pyc
jsonattrs/migrations/__pycache__/0002_attribute_choice_labels.cpython-35.pyc
jsonattrs/migrations/__pycache__/0003_prepare_multilingual_setup.cpython-35.pyc
jsonattrs/migrations/__pycache__/0004_convert_multilingual_fields.cpython-35.pyc
jsonattrs/migrations/__pycache__/0005_remove_monolingual_fields.cpython-35.pyc
jsonattrs/migrations/__pycache__/0006_make_default_field_nullable.cpython-35.pyc
jsonattrs/migrations/__pycache__/__init__.cpython-35.pyc
